hazm_normalizer/__init__.py
hazm_normalizer/lemmatizer.py
hazm_normalizer/normalizer.py
hazm_normalizer/stemmer.py
hazm_normalizer/utils.py
hazm_normalizer/word_tokenizer.py
hazm_normalizer/data/abbreviations.dat
hazm_normalizer/data/iverbs.dat
hazm_normalizer/data/iwords.dat
hazm_normalizer/data/stopwords.dat
hazm_normalizer/data/verbs.dat
hazm_normalizer/data/words.dat
hazm_normalizer-0.3.0.dist-info/LICENSE
hazm_normalizer-0.3.0.dist-info/METADATA
hazm_normalizer-0.3.0.dist-info/WHEEL
hazm_normalizer-0.3.0.dist-info/top_level.txt
hazm_normalizer-0.3.0.dist-info/RECORD
