Metadata-Version: 2.1
Name: hazm-normalizer
Version: 0.3.0
Classifier: Programming Language :: Python :: 3
Classifier: License :: OSI Approved :: MIT License
Classifier: Operating System :: OS Independent
License-File: LICENSE
Requires-Dist: nltk
Requires-Dist: flashtext
